Metadata-Version: 2.1
Name: scrapy-dot-items
Version: 0.1.0
Summary: A Scrapy addon that allows to access arguments via the dot
Home-page: https://github.com/sgerodes/scrapy-items
Author: Sergey Gerodes
Author-email: sgerodes@gmail.com
Keywords: python,scrapy,scrapy-items,dot-items,dot
Classifier: Programming Language :: Python :: 3
Classifier: Programming Language :: Python :: 3.6
Classifier: Operating System :: Unix
Classifier: Operating System :: MacOS :: MacOS X
Classifier: Operating System :: Microsoft :: Windows
Requires-Python: >=3.6
